discordcache/__init__.py
discordcache/__main__.py
discordcache/cache.py
discordcache/cli.py
discordcache/crypto.py
discord_cache-1.0.0.dist-info/METADATA
discord_cache-1.0.0.dist-info/WHEEL
discord_cache-1.0.0.dist-info/top_level.txt
discord_cache-1.0.0.dist-info/RECORD
