Metadata-Version: 2.1
Name: discord-cache
Version: 1.0.0
Summary: A better way to boost youre discord bot performace.
Author: ryzmae
Author-email: ryzmae <contact@ryzm.tech>
Project-URL: Homepage, https://github.com/ryzmae/discord-cache
Project-URL: Bug Tracker, https://github.com/ryzmae/discord-cache/issues
Keywords: python,discord-cache,discord,cache,caching
Classifier: Programming Language :: Python :: 3
Classifier: License :: OSI Approved :: MIT License
Classifier: Operating System :: OS Independent
Requires-Python: >=3.9
Requires-Dist: redis-py
Requires-Dist: pymongo
Requires-Dist: colorama
Requires-Dist: typer
Requires-Dist: pycryptodome
Requires-Dist: rich
Requires-Dist: pyyaml
